{
  "id": "90d25c5c-a2a6-4e44-9e14-4c7f0b9a8770",
  "prevId": "598fc72d-58e0-4714-a560-c76ba752286c",
  "version": "7",
  "dialect": "postgresql",
  "tables": {
    "public.audit_log": {
      "name": "audit_log",
      "schema": "",
      "columns": {
        "id": {
          "name": "id",
          "type": "serial",
          "primaryKey": true,
          "notNull": true
        },
        "userId": {
          "name": "userId",
          "type": "integer",
          "primaryKey": false,
          "notNull": false
        },
        "action": {
          "name": "action",
          "type": "varchar(100)",
          "primaryKey": false,
          "notNull": true
        },
        "entityType": {
          "name": "entityType",
          "type": "varchar(50)",
          "primaryKey": false,
          "notNull": true
        },
        "entityId": {
          "name": "entityId",
          "type": "integer",
          "primaryKey": false,
          "notNull": false
        },
        "details": {
          "name": "details",
          "type": "text",
          "primaryKey": false,
          "notNull": false
        },
        "createdAt": {
          "name": "createdAt",
          "type": "timestamp",
          "primaryKey": false,
          "notNull": true,
          "default": "now()"
        }
      },
      "indexes": {},
      "foreignKeys": {},
      "compositePrimaryKeys": {},
      "uniqueConstraints": {},
      "policies": {},
      "checkConstraints": {},
      "isRLSEnabled": false
    },
    "public.cranes": {
      "name": "cranes",
      "schema": "",
      "columns": {
        "id": {
          "name": "id",
          "type": "serial",
          "primaryKey": true,
          "notNull": true
        },
        "name": {
          "name": "name",
          "type": "varchar(255)",
          "primaryKey": false,
          "notNull": true
        },
        "capacity": {
          "name": "capacity",
          "type": "numeric(10, 2)",
          "primaryKey": false,
          "notNull": true
        },
        "maxPoolWidth": {
          "name": "maxPoolWidth",
          "type": "numeric(6, 2)",
          "primaryKey": false,
          "notNull": false
        },
        "description": {
          "name": "description",
          "type": "text",
          "primaryKey": false,
          "notNull": false
        },
        "location": {
          "name": "location",
          "type": "varchar(255)",
          "primaryKey": false,
          "notNull": false
        },
        "isActive": {
          "name": "isActive",
          "type": "boolean",
          "primaryKey": false,
          "notNull": true,
          "default": true
        },
        "updatedAt": {
          "name": "updatedAt",
          "type": "timestamp",
          "primaryKey": false,
          "notNull": true,
          "default": "now()"
        }
      },
      "indexes": {},
      "foreignKeys": {},
      "compositePrimaryKeys": {},
      "uniqueConstraints": {},
      "policies": {},
      "checkConstraints": {},
      "isRLSEnabled": false
    },
    "public.reservations": {
      "name": "reservations",
      "schema": "",
      "columns": {
        "id": {
          "name": "id",
          "type": "serial",
          "primaryKey": true,
          "notNull": true
        },
        "userId": {
          "name": "userId",
          "type": "integer",
          "primaryKey": false,
          "notNull": true
        },
        "craneId": {
          "name": "craneId",
          "type": "integer",
          "primaryKey": false,
          "notNull": true
        },
        "startDate": {
          "name": "startDate",
          "type": "timestamp",
          "primaryKey": false,
          "notNull": true
        },
        "endDate": {
          "name": "endDate",
          "type": "timestamp",
          "primaryKey": false,
          "notNull": true
        },
        "status": {
          "name": "status",
          "type": "status",
          "typeSchema": "public",
          "primaryKey": false,
          "notNull": true,
          "default": "'pending'"
        },
        "reservationNumber": {
          "name": "reservationNumber",
          "type": "varchar(20)",
          "primaryKey": false,
          "notNull": false
        },
        "vesselId": {
          "name": "vesselId",
          "type": "integer",
          "primaryKey": false,
          "notNull": false
        },
        "isMaintenance": {
          "name": "isMaintenance",
          "type": "boolean",
          "primaryKey": false,
          "notNull": true,
          "default": false
        },
        "reminderSent": {
          "name": "reminderSent",
          "type": "boolean",
          "primaryKey": false,
          "notNull": true,
          "default": false
        },
        "vesselType": {
          "name": "vesselType",
          "type": "vessel_type",
          "typeSchema": "public",
          "primaryKey": false,
          "notNull": false
        },
        "vesselLength": {
          "name": "vesselLength",
          "type": "numeric(7, 2)",
          "primaryKey": false,
          "notNull": false
        },
        "vesselWidth": {
          "name": "vesselWidth",
          "type": "numeric(6, 2)",
          "primaryKey": false,
          "notNull": false
        },
        "vesselDraft": {
          "name": "vesselDraft",
          "type": "numeric(5, 2)",
          "primaryKey": false,
          "notNull": false
        },
        "vesselWeight": {
          "name": "vesselWeight",
          "type": "numeric(8, 2)",
          "primaryKey": false,
          "notNull": false
        },
        "vesselName": {
          "name": "vesselName",
          "type": "varchar(255)",
          "primaryKey": false,
          "notNull": false
        },
        "liftPurpose": {
          "name": "liftPurpose",
          "type": "text",
          "primaryKey": false,
          "notNull": false
        },
        "contactPhone": {
          "name": "contactPhone",
          "type": "varchar(50)",
          "primaryKey": false,
          "notNull": false
        },
        "adminNotes": {
          "name": "adminNotes",
          "type": "text",
          "primaryKey": false,
          "notNull": false
        },
        "reviewedBy": {
          "name": "reviewedBy",
          "type": "integer",
          "primaryKey": false,
          "notNull": false
        },
        "reviewedAt": {
          "name": "reviewedAt",
          "type": "timestamp",
          "primaryKey": false,
          "notNull": false
        },
        "createdAt": {
          "name": "createdAt",
          "type": "timestamp",
          "primaryKey": false,
          "notNull": true,
          "default": "now()"
        },
        "updatedAt": {
          "name": "updatedAt",
          "type": "timestamp",
          "primaryKey": false,
          "notNull": true,
          "default": "now()"
        }
      },
      "indexes": {},
      "foreignKeys": {},
      "compositePrimaryKeys": {},
      "uniqueConstraints": {
        "reservations_reservationNumber_unique": {
          "name": "reservations_reservationNumber_unique",
          "nullsNotDistinct": false,
          "columns": [
            "reservationNumber"
          ]
        }
      },
      "policies": {},
      "checkConstraints": {},
      "isRLSEnabled": false
    },
    "public.settings": {
      "name": "settings",
      "schema": "",
      "columns": {
        "key": {
          "name": "key",
          "type": "varchar(100)",
          "primaryKey": true,
          "notNull": true
        },
        "value": {
          "name": "value",
          "type": "text",
          "primaryKey": false,
          "notNull": true
        },
        "updatedAt": {
          "name": "updatedAt",
          "type": "timestamp",
          "primaryKey": false,
          "notNull": true,
          "default": "now()"
        }
      },
      "indexes": {},
      "foreignKeys": {},
      "compositePrimaryKeys": {},
      "uniqueConstraints": {},
      "policies": {},
      "checkConstraints": {},
      "isRLSEnabled": false
    },
    "public.users": {
      "name": "users",
      "schema": "",
      "columns": {
        "id": {
          "name": "id",
          "type": "serial",
          "primaryKey": true,
          "notNull": true
        },
        "openId": {
          "name": "openId",
          "type": "varchar(64)",
          "primaryKey": false,
          "notNull": false
        },
        "passwordHash": {
          "name": "passwordHash",
          "type": "varchar(255)",
          "primaryKey": false,
          "notNull": false
        },
        "firstName": {
          "name": "firstName",
          "type": "varchar(100)",
          "primaryKey": false,
          "notNull": false
        },
        "lastName": {
          "name": "lastName",
          "type": "varchar(100)",
          "primaryKey": false,
          "notNull": false
        },
        "name": {
          "name": "name",
          "type": "text",
          "primaryKey": false,
          "notNull": false
        },
        "email": {
          "name": "email",
          "type": "varchar(320)",
          "primaryKey": false,
          "notNull": false
        },
        "loginMethod": {
          "name": "loginMethod",
          "type": "varchar(64)",
          "primaryKey": false,
          "notNull": false
        },
        "role": {
          "name": "role",
          "type": "role",
          "typeSchema": "public",
          "primaryKey": false,
          "notNull": true,
          "default": "'user'"
        },
        "phone": {
          "name": "phone",
          "type": "varchar(50)",
          "primaryKey": false,
          "notNull": false
        },
        "createdAt": {
          "name": "createdAt",
          "type": "timestamp",
          "primaryKey": false,
          "notNull": true,
          "default": "now()"
        },
        "updatedAt": {
          "name": "updatedAt",
          "type": "timestamp",
          "primaryKey": false,
          "notNull": true,
          "default": "now()"
        },
        "lastSignedIn": {
          "name": "lastSignedIn",
          "type": "timestamp",
          "primaryKey": false,
          "notNull": true,
          "default": "now()"
        }
      },
      "indexes": {},
      "foreignKeys": {},
      "compositePrimaryKeys": {},
      "uniqueConstraints": {
        "users_openId_unique": {
          "name": "users_openId_unique",
          "nullsNotDistinct": false,
          "columns": [
            "openId"
          ]
        },
        "users_email_unique": {
          "name": "users_email_unique",
          "nullsNotDistinct": false,
          "columns": [
            "email"
          ]
        }
      },
      "policies": {},
      "checkConstraints": {},
      "isRLSEnabled": false
    },
    "public.vessels": {
      "name": "vessels",
      "schema": "",
      "columns": {
        "id": {
          "name": "id",
          "type": "serial",
          "primaryKey": true,
          "notNull": true
        },
        "ownerId": {
          "name": "ownerId",
          "type": "integer",
          "primaryKey": false,
          "notNull": true
        },
        "name": {
          "name": "name",
          "type": "varchar(255)",
          "primaryKey": false,
          "notNull": true
        },
        "type": {
          "name": "type",
          "type": "vessel_type",
          "typeSchema": "public",
          "primaryKey": false,
          "notNull": true
        },
        "length": {
          "name": "length",
          "type": "numeric(7, 2)",
          "primaryKey": false,
          "notNull": false
        },
        "width": {
          "name": "width",
          "type": "numeric(6, 2)",
          "primaryKey": false,
          "notNull": false
        },
        "draft": {
          "name": "draft",
          "type": "numeric(5, 2)",
          "primaryKey": false,
          "notNull": false
        },
        "weight": {
          "name": "weight",
          "type": "numeric(8, 2)",
          "primaryKey": false,
          "notNull": false
        },
        "createdAt": {
          "name": "createdAt",
          "type": "timestamp",
          "primaryKey": false,
          "notNull": true,
          "default": "now()"
        },
        "updatedAt": {
          "name": "updatedAt",
          "type": "timestamp",
          "primaryKey": false,
          "notNull": true,
          "default": "now()"
        }
      },
      "indexes": {},
      "foreignKeys": {},
      "compositePrimaryKeys": {},
      "uniqueConstraints": {},
      "policies": {},
      "checkConstraints": {},
      "isRLSEnabled": false
    },
    "public.waiting_list": {
      "name": "waiting_list",
      "schema": "",
      "columns": {
        "id": {
          "name": "id",
          "type": "serial",
          "primaryKey": true,
          "notNull": true
        },
        "userId": {
          "name": "userId",
          "type": "integer",
          "primaryKey": false,
          "notNull": true
        },
        "craneId": {
          "name": "craneId",
          "type": "integer",
          "primaryKey": false,
          "notNull": true
        },
        "requestedDate": {
          "name": "requestedDate",
          "type": "date",
          "primaryKey": false,
          "notNull": true
        },
        "slotCount": {
          "name": "slotCount",
          "type": "integer",
          "primaryKey": false,
          "notNull": true,
          "default": 1
        },
        "vesselData": {
          "name": "vesselData",
          "type": "jsonb",
          "primaryKey": false,
          "notNull": false
        },
        "notified": {
          "name": "notified",
          "type": "boolean",
          "primaryKey": false,
          "notNull": true,
          "default": false
        },
        "createdAt": {
          "name": "createdAt",
          "type": "timestamp",
          "primaryKey": false,
          "notNull": true,
          "default": "now()"
        }
      },
      "indexes": {},
      "foreignKeys": {},
      "compositePrimaryKeys": {},
      "uniqueConstraints": {},
      "policies": {},
      "checkConstraints": {},
      "isRLSEnabled": false
    }
  },
  "enums": {
    "public.role": {
      "name": "role",
      "schema": "public",
      "values": [
        "user",
        "admin"
      ]
    },
    "public.status": {
      "name": "status",
      "schema": "public",
      "values": [
        "pending",
        "approved",
        "rejected",
        "cancelled"
      ]
    },
    "public.vessel_type": {
      "name": "vessel_type",
      "schema": "public",
      "values": [
        "sailboat",
        "motorboat",
        "catamaran"
      ]
    }
  },
  "schemas": {},
  "sequences": {},
  "roles": {},
  "policies": {},
  "views": {},
  "_meta": {
    "columns": {},
    "schemas": {},
    "tables": {}
  }
}